LICENSE
MANIFEST.in
README.rst
requirements.txt
setup.py
nbrequests/__init__.py
nbrequests.egg-info/PKG-INFO
nbrequests.egg-info/SOURCES.txt
nbrequests.egg-info/dependency_links.txt
nbrequests.egg-info/requires.txt
nbrequests.egg-info/top_level.txt
nbrequests/templates/requests.html
nbrequests/templates/requests.js