Metadata-Version: 1.1
Name: nbrequests
Version: 0.0.8
Summary: Display requests in Jupyter Notebook
Home-page: http://github.com/kristianperkins/nbrequests
Author: Kristian Perkins
Author-email: khperkins@gmail.com
License: Apache 2.0
Keywords: requests jupyter rest json
Platform: UNKNOWN
Classifier: Environment :: Console
Classifier: Development Status :: 3 - Alpha
Classifier: License :: OSI Approved :: Apache Software License
Classifier: Topic :: Utilities
Classifier: Operating System :: OS Independent
Classifier: Programming Language :: Python :: 3
Classifier: Intended Audience :: Developers
Classifier: Framework :: Jupyter
